health_check_email/__init__.py
health_check_email/apps.py
health_check_email/backends.py
health_check_email/conf.py
django_health_check_email-0.1.0.dist-info/LICENSE
django_health_check_email-0.1.0.dist-info/WHEEL
django_health_check_email-0.1.0.dist-info/METADATA
django_health_check_email-0.1.0.dist-info/RECORD
