Metadata-Version: 2.1
Name: django-health-check-email
Version: 0.1.0
Summary: Add email check to django-health-check.
Home-page: https://www.ubicast.eu
License: MIT
Keywords: django,monitoring,health,email
Author: Nicolas KAROLAK
Author-email: nicolas.karolak@ubicast.eu
Requires-Python: >=3.6,<4.0
Classifier: Environment :: Web Environment
Classifier: Framework :: Django
Classifier: Framework :: Django :: 2.2
Classifier: License :: OSI Approved :: MIT License
Classifier: Programming Language :: Python :: 3
Classifier: Programming Language :: Python :: 3.6
Classifier: Programming Language :: Python :: 3.7
Requires-Dist: django-health-check (>=3.9,<4.0)
Project-URL: Repository, https://github.com/UbiCastTeam/djang-health-check-email
